multi_repo_automation/__init__.py
multi_repo_automation/commented_yaml.py
multi_repo_automation/editor.py
multi_repo_automation/tools.py
multi_repo_automation-1.7.0.dist-info/LICENSE
multi_repo_automation-1.7.0.dist-info/METADATA
multi_repo_automation-1.7.0.dist-info/WHEEL
multi_repo_automation-1.7.0.dist-info/entry_points.txt
multi_repo_automation-1.7.0.dist-info/RECORD
