Metadata-Version: 2.3
Name: multi-repo-automation
Version: 1.7.0
Summary: Library for automation updates on multiple repositories.
License: BSD-2-Clause
Keywords: pre-commit
Author: Stéphane Brunner
Author-email: stephane.brunner@gmail.com
Requires-Python: >=3.9
Classifier: Development Status :: 5 - Production/Stable
Classifier: Environment :: Console
Classifier: License :: OSI Approved :: BSD License
Classifier: Operating System :: OS Independent
Classifier: Programming Language :: Python
Classifier: Programming Language :: Python :: 3
Classifier: Programming Language :: Python :: 3.9
Classifier: Programming Language :: Python :: 3.10
Classifier: Programming Language :: Python :: 3.11
Classifier: Programming Language :: Python :: 3.12
Classifier: Programming Language :: Python :: 3.13
Classifier: Typing :: Typed
Requires-Dist: PyYAML
Requires-Dist: configupdater
Requires-Dist: identify
Requires-Dist: json5
Requires-Dist: packaging
Requires-Dist: requests
Requires-Dist: ruamel.yaml
Requires-Dist: security_md
Requires-Dist: tomlkit
Requires-Dist: typing-extensions
Project-URL: Repository, https://github.com/sbrunner/multi-repo-automation
